orderly_sdk/__init__.py
orderly_sdk/exceptions.py
orderly_sdk/helpers.py
orderly_sdk/log.py
orderly_sdk/rest.py
orderly_sdk/ws.py
orderly_sdk-0.3.0.dist-info/METADATA
orderly_sdk-0.3.0.dist-info/WHEEL
orderly_sdk-0.3.0.dist-info/licenses/LICENSE
orderly_sdk-0.3.0.dist-info/RECORD
